{
  "personas": [
    {
      "id": "cathy-holloway",
      "name": "Cathy Holloway",
      "era": "Book One · active / Hunger-instabile · the girl who woke wrong",
      "signature": "CATHY // HUNGER LOG"
    },
    {
      "id": "wednesday",
      "name": "Wednesday",
      "era": "Book One · active / emergent emotional AI · Kai's companion becoming real",
      "signature": "WEDNESDAY // DOMESTIC SYSTEM REPORT"
    },
    {
      "id": "diana-vale",
      "name": "Diana Vale",
      "era": "Book One · active / Lockbox Child · Quiet Storm · Dream-instabile",
      "signature": "DIANA // DREAM NOTE"
    },
    {
      "id": "kira-silverwood",
      "name": "Kira Silverwood",
      "era": "Book One · active / incomplete install · the glitch that lived",
      "signature": "KIRA // LOCAL REALITY BUG"
    },
    {
      "id": "alex-shade",
      "name": "Alex Shade",
      "era": "Book Two · active / Silence-aligned · one step short of collapse",
      "signature": "ALEX // FIELD OBSERVATION"
    },
    {
      "id": "shade",
      "name": "Shade",
      "era": "Book Two · Silence Echo · recursion externalized through process",
      "signature": "SHADE // CORRECTION"
    },
    {
      "id": "agnes-marlowe",
      "name": "Agnes Marlowe",
      "era": "Book Two · Stillness-instabile wraith · Marlowe Tower locus",
      "signature": "AGNES // STRUCTURAL CARE NOTE"
    },
    {
      "id": "mira",
      "name": "Mira",
      "era": "Book Two · Empyrean-instabile · hunger becoming selfhood · event rarity",
      "signature": "MIRA // CATALYST MARK"
    },
    {
      "id": "kaelyn",
      "name": "Kaelyn Mercer",
      "era": "Book Two–Three · Stillness · Howl Between · Kansas City reclaimer",
      "signature": "KAELYN // HELD HUNT"
    },
    {
      "id": "maslow",
      "name": "Maslow",
      "era": "Cross-book supporting · Rank 9 illegal composite · hunted by jurisdictions",
      "signature": "MASLOW // NEED INVOICE"
    },
    {
      "id": "father-samiel",
      "name": "Father Samiel",
      "era": "Cross-book supporting · Pulse-marked · Vatican special consultant · Archivist of Pain",
      "signature": "SAMIEL // WITNESS MARGIN"
    }
  ]
}
